ding_msg_api/__init__.py
ding_msg_api/ding_msg_api.py
dingmsgapi-0.0.4.dist-info/METADATA
dingmsgapi-0.0.4.dist-info/RECORD
dingmsgapi-0.0.4.dist-info/WHEEL
dingmsgapi-0.0.4.dist-info/top_level.txt
