Metadata-Version: 2.1
Name: dingmsgapi
Version: 0.0.4
Summary: Python dingding msg api
Home-page: https://github.com/littlegrow/dingmsgapi
Author: littlegrow
Author-email: kfliuleigang@sina.com
License: UNKNOWN
Project-URL: Blog, https://littlegrow.top
Keywords: dingding
Platform: UNKNOWN
Classifier: Programming Language :: Python :: 2.7
